repo2mono/__init__.py
repo2mono/cli.py
repo2mono/process.py
repo2mono-0.1.1.dist-info/METADATA
repo2mono-0.1.1.dist-info/WHEEL
repo2mono-0.1.1.dist-info/entry_points.txt
repo2mono-0.1.1.dist-info/RECORD
