Metadata-Version: 2.1
Name: repo2mono
Version: 0.1.1
Summary: Codebase to single Markdown string with file tree.
Author: jaredkirby
Author-email: jpeterkirby@gmail.com
Requires-Python: >=3.8,<4.0
Classifier: Programming Language :: Python :: 3
Classifier: Programming Language :: Python :: 3.8
Classifier: Programming Language :: Python :: 3.9
Classifier: Programming Language :: Python :: 3.10
Classifier: Programming Language :: Python :: 3.11
Classifier: Programming Language :: Python :: 3.12
Requires-Dist: click (>=8.0,<9.0)
